{
  "categories": [
    {
      "name": 0,
      "items": [
        {
          "id": 1,
          "name": "کیک وانیلی",
          "description": "وانیل",
          "image": "/Products/cake-16.png",
          "price": 78
        }
      ]
    },
    {
      "name": 1,
      "items": [
        {
          "id": 1,
          "name": "پیتزا",
          "description": "گوشت ، قارچ ، فلفل دلمه ",
          "image": "/Products/pizza.png",
          "price": 290
        },
        {
          "id": 2,
          "name": "پیتزا",
          "description": "گوشت ، قارچ ، فلفل دلمه ",
          "image": "/Products/pizza.png",
          "price": 290
        },
        {
          "id": 3,
          "name": "پیتزا",
          "description": "گوشت ، قارچ ، فلفل دلمه ",
          "image": "/Products/pizza.png",
          "price": 290
        }
      ]
    },

    {
      "name": 2,
      "items": [
        {
          "id": 5,
          "name": "لیموناد",
          "description": "لیمو",
          "image": "/Products/limo.png",
          "price": 88
        },
        {
          "id": 1,
          "name": "لیموناد",
          "description": "لیمو",
          "image": "/Products/limo.png",
          "price": 88
        },
        {
          "id": 2,
          "name": "لیموناد",
          "description": "لیمو",
          "image": "/Products/limo.png",
          "price": 88
        },
        {
          "id": 3,
          "name": "لیموناد",
          "description": "لیمو",
          "image": "/Products/limo.png",
          "price": 88
        }
      ]
    },

    {
      "name": 3,
      "items": [
        {
          "id": 1,
          "name": "اسپرسو",
          "description": "دبل",
          "image": "/Products/coffe.jpg",
          "price": 70
        },
        {
          "id": 2,
          "name": "اسپرسو",
          "description": "سینگل",
          "image": "/Products/coffe.jpg",
          "price": 70
        },
        {
          "id": 3,
          "name": "کاپوچینو",
          "description": "دبل",
          "image": "/Products/coffe.jpg",
          "price": 70
        }
      ]
    }
  ]
}
